README.md
setup.py
pch/__init__.py
pch/check_env_template.py
pch/check_missed_migrations.py
pch/check_untracked.py
pch/utils.py
pch.egg-info/PKG-INFO
pch.egg-info/SOURCES.txt
pch.egg-info/dependency_links.txt
pch.egg-info/entry_points.txt
pch.egg-info/requires.txt
pch.egg-info/top_level.txt